runningz_so/.gitignore
runningz_so/__init__.pyc
runningz_so/api.cpython-39-x86_64-linux-gnu.so
runningz_so/core/DataMaster.cpython-39-x86_64-linux-gnu.so
runningz_so/core/__init__.pyc
runningz_so/core/api.cpython-39-x86_64-linux-gnu.so
runningz_so/core/er/__init__.pyc
runningz_so/core/er/hasher.cpython-39-x86_64-linux-gnu.so
runningz_so/core/er/idxer.cpython-39-x86_64-linux-gnu.so
runningz_so/core/er/masker.cpython-39-x86_64-linux-gnu.so
runningz_so/core/er/namer.cpython-39-x86_64-linux-gnu.so
runningz_so/core/er/scaler.cpython-39-x86_64-linux-gnu.so
runningz_so/core/op/OPMaster.cpython-39-x86_64-linux-gnu.so
runningz_so/core/op/OPMaster_py.cpython-39-x86_64-linux-gnu.so
runningz_so/core/op/__init__.pyc
runningz_so/core/op/__init___py.cpython-39-x86_64-linux-gnu.so
runningz_so/core/op/_numba.pyc
runningz_so/core/op/_numba_1.pyc
runningz_so/core/op/_numba_2.pyc
runningz_so/core/op/_numba_2_2.pyc
runningz_so/core/op/_numba_m.pyc
runningz_so/core/op/_numba_m_py.pyc
runningz_so/core/op/_numba_merge_roll.pyc
runningz_so/core/op/op_1.cpython-39-x86_64-linux-gnu.so
runningz_so/core/op/op_1_numba.pyc
runningz_so/core/op/op_1_numba_old.pyc
runningz_so/core/op/op_2.cpython-39-x86_64-linux-gnu.so
runningz_so/core/op/op_2_numba.pyc
runningz_so/core/op/op_3.cpython-39-x86_64-linux-gnu.so
runningz_so/core/op/op_3_numba.pyc
runningz_so/core/op/op_groupby.cpython-39-x86_64-linux-gnu.so
runningz_so/core/op/op_m.cpython-39-x86_64-linux-gnu.so
runningz_so/core/op/op_m_numba.pyc
runningz_so/core/op/op_other.cpython-39-x86_64-linux-gnu.so
runningz_so/fe/.gitignore
runningz_so/fe/FEMaster.cpython-39-x86_64-linux-gnu.so
runningz_so/fe/FEMaster_py.cpython-39-x86_64-linux-gnu.so
runningz_so/fe/__init__.pyc
runningz_so/fe/fe_dump.cpython-39-x86_64-linux-gnu.so
runningz_so/fe/fe_dump.ipynb
runningz_so/fe/fe_dump_py.cpython-39-x86_64-linux-gnu.so
runningz_so/fe/fe_eval.cpython-39-x86_64-linux-gnu.so
runningz_so/fe/fe_eval_py.cpython-39-x86_64-linux-gnu.so
runningz-0.17.9.dist-info/METADATA
runningz-0.17.9.dist-info/WHEEL
runningz-0.17.9.dist-info/entry_points.txt
runningz-0.17.9.dist-info/native_libs.txt
runningz-0.17.9.dist-info/top_level.txt
runningz-0.17.9.dist-info/RECORD
