Metadata-Version: 2.1
Name: runningz
Version: 0.17.9
Summary: fe_master_runningz
Home-page: https://github.com/RunxingZhong/
Author: runningz
Author-email: zhongrunxing@gmail.com
License: MIT
Platform: UNKNOWN
Requires-Python: >=3.9
Requires-Dist: psutil
Requires-Dist: tqdm
Requires-Dist: ipywidgets
Requires-Dist: scipy
Requires-Dist: numpy
Requires-Dist: pandas
Requires-Dist: scikit-learn
Requires-Dist: numba
Requires-Dist: pyyaml
Requires-Dist: chinese-calendar
Requires-Dist: seaborn
Requires-Dist: polars
Requires-Dist: pyarrow
Requires-Dist: torch
Requires-Dist: tushare
Requires-Dist: requests
Requires-Dist: lightgbm
Requires-Dist: catboost
Requires-Dist: xgboost
Requires-Dist: optuna
Requires-Dist: cvxpy
Requires-Dist: MOSEK
